{
  "Comment": "This command info is generated from fig",
  "Name": "afplay",
  "Description": "Audio File Play",
  "Arguments": [
    {
      "Arguments": [
        {
          "Name": "-v",
          "Description": "Set the volume for playback of the file\nApple does not define a value range for this, but it appears to accept\n0=silent, 1=normal (default) and then up to 255=Very loud.\nThe scale is logarithmic and in addition to (not a replacement for) other volume control(s)",
          "Aliases": [
            "--volume"
          ],
          "Arguments": [
            {
              "Arguments": [
                {
                  "Name": "0 (silent) - 1 (normal) - 255 (very loud)",
                  "Description": "0 (silent) - 1 (normal) - 255 (very loud)",
                  "Type": "String"
                }
              ]
            }
          ]
        },
        {
          "Name": "-h",
          "Description": "Print help",
          "Aliases": [
            "--help"
          ],
          "Arguments": []
        },
        {
          "Name": "--leaks",
          "Description": "Run leaks analysis",
          "Aliases": [],
          "Arguments": []
        },
        {
          "Name": "-t",
          "Description": "Play for \u0060TIME\u0060 seconds\n\u003E0 and \u003C duration of \u0060audio_file\u0060",
          "Aliases": [
            "--time"
          ],
          "Arguments": [
            {
              "Arguments": [
                {
                  "Name": "TIME",
                  "Description": "TIME",
                  "Type": "String"
                }
              ]
            }
          ]
        },
        {
          "Name": "-r",
          "Description": "Play at playback \u0060RATE\u0060.\npractical limits are about 0.4 (slower) to 3.0 (faster)",
          "Aliases": [
            "--rate"
          ],
          "Arguments": [
            {
              "Arguments": [
                {
                  "Name": "RATE",
                  "Description": "RATE",
                  "Type": "String"
                }
              ]
            }
          ]
        },
        {
          "Name": "-q",
          "Description": "Set the quality used for rate-scaled playback (default is 0 - low quality, 1 - high quality)",
          "Aliases": [
            "--rQuality"
          ],
          "Arguments": [
            {
              "Arguments": [
                {
                  "Name": "QUALITY",
                  "Description": "QUALITY",
                  "Type": "String"
                }
              ]
            }
          ]
        },
        {
          "Name": "-d",
          "Description": "Debug print output",
          "Aliases": [
            "--debug"
          ],
          "Arguments": []
        }
      ],
      "Optional": true
    },
    {
      "Arguments": [
        {
          "Name": "play the song in the path",
          "Description": "play the song in the path",
          "Type": "FileSystemEntry"
        }
      ]
    }
  ]
}