{
  "Comment": "This command info is generated from fig",
  "Name": "oxlint",
  "Description": "A high performance linter for the Oxidation Compiler",
  "Arguments": [
    {
      "Arguments": [
        {
          "Name": "-c",
          "Description": "Path to Oxlint JSON configuration file",
          "Aliases": [
            "--config"
          ],
          "Arguments": [
            {
              "Arguments": [
                {
                  "Name": "file",
                  "Description": "file",
                  "Type": "String",
                  "Extensions": [],
                  "CustomCommand": ""
                }
              ]
            }
          ]
        },
        {
          "Name": "--tsconfig",
          "Description": "Path to tsconfig.json path for reading path aliases and project references for import plugin",
          "Aliases": [],
          "Arguments": [
            {
              "Arguments": [
                {
                  "Name": "file",
                  "Description": "file",
                  "Type": "CustomArgument",
                  "Extensions": [],
                  "CustomCommand": "ls"
                }
              ]
            }
          ]
        },
        {
          "Name": "--ignore-path",
          "Description": "Specify the file to use as your .eslintignore",
          "Aliases": [],
          "Arguments": [
            {
              "Arguments": [
                {
                  "Name": "file",
                  "Description": "file",
                  "Type": "FileSystemEntry"
                },
                {
                  "Name": ".eslintignore",
                  "Description": "file"
                }
              ]
            }
          ]
        },
        {
          "Name": "--ignore-pattern",
          "Description": "Specify file patterns to ignore (in addition to those in .eslintignore)",
          "Aliases": [],
          "Arguments": [
            {
              "Arguments": [
                {
                  "Name": "pattern",
                  "Description": "pattern",
                  "Type": "String"
                }
              ]
            }
          ]
        },
        {
          "Name": "--no-ignore",
          "Description": "Disable exluding of files from .eslintignore files, --ignore-path, and --ignore-pattern",
          "Aliases": [],
          "Arguments": []
        },
        {
          "Name": "--symlinks",
          "Description": "Follow symlinks when linting, which are ignored by default",
          "Aliases": [],
          "Arguments": []
        },
        {
          "Name": "--jsdoc-plugin",
          "Description": "Enable the JSDoc plugin",
          "Aliases": [],
          "Arguments": []
        },
        {
          "Name": "--jest-plugin",
          "Description": "Enable the Jest plugin",
          "Aliases": [],
          "Arguments": []
        },
        {
          "Name": "--vitest-plugin",
          "Description": "Enable the Vitest plugin",
          "Aliases": [],
          "Arguments": []
        },
        {
          "Name": "--nextjs-plugin",
          "Description": "Enable the Next.js plugin",
          "Aliases": [],
          "Arguments": []
        },
        {
          "Name": "--react-perf-plugin",
          "Description": "Enable the React Performance plugin",
          "Aliases": [],
          "Arguments": []
        },
        {
          "Name": "--promise-plugin",
          "Description": "Enable the Promise plugin",
          "Aliases": [],
          "Arguments": []
        },
        {
          "Name": "--disable-react-plugin",
          "Description": "Disable the React plugin, which is turned on by default",
          "Aliases": [],
          "Arguments": []
        },
        {
          "Name": "--disable-unicorn-plugin",
          "Description": "Disable the Unicorn plugin, which is turned on by default",
          "Aliases": [],
          "Arguments": []
        },
        {
          "Name": "--disable-oxc-plugin",
          "Description": "Disable the Oxc plugin, which is turned on by default",
          "Aliases": [],
          "Arguments": []
        },
        {
          "Name": "--disable-typescript-plugin",
          "Description": "Disable the TypeScript plugin, which is turned on by default",
          "Aliases": [],
          "Arguments": []
        },
        {
          "Name": "--disable-import-plugin",
          "Description": "Disable the Import plugin, which is turned on by default",
          "Aliases": [],
          "Arguments": []
        },
        {
          "Name": "-D",
          "Description": "Deny a lint rule or category (enable a lint as an error)",
          "Aliases": [
            "--deny"
          ],
          "Arguments": [
            {
              "Arguments": [
                {
                  "Name": "lint",
                  "Description": "lint",
                  "Type": "String",
                  "Extensions": [],
                  "CustomCommand": ""
                }
              ]
            }
          ]
        },
        {
          "Name": "-W",
          "Description": "Warn about a lint rule or category (enable a lint as a warning)",
          "Aliases": [
            "--warn"
          ],
          "Arguments": [
            {
              "Arguments": [
                {
                  "Name": "lint",
                  "Description": "lint",
                  "Type": "String",
                  "Extensions": [],
                  "CustomCommand": ""
                }
              ]
            }
          ]
        },
        {
          "Name": "-A",
          "Description": "Allow a lint rule or category (suppress a lint)",
          "Aliases": [
            "--allow"
          ],
          "Arguments": [
            {
              "Arguments": [
                {
                  "Name": "lint",
                  "Description": "lint",
                  "Type": "String",
                  "Extensions": [],
                  "CustomCommand": ""
                }
              ]
            }
          ]
        },
        {
          "Name": "--fix",
          "Description": "Fix as many issues as possible. Only unfixed issues are reported in the output",
          "Aliases": [],
          "Arguments": []
        },
        {
          "Name": "--silent",
          "Description": "Do not display any diagnostics",
          "Aliases": [],
          "Arguments": []
        },
        {
          "Name": "--deny-warnings",
          "Description": "Exit with a non-zero code if there are any warnings",
          "Aliases": [],
          "Arguments": []
        },
        {
          "Name": "--max-warnings",
          "Description": "Exit with a non-zero code if there are more than \u0060max\u0060 warnings",
          "Aliases": [],
          "Arguments": [
            {
              "Arguments": [
                {
                  "Name": "max",
                  "Description": "max",
                  "Type": "String"
                }
              ]
            }
          ]
        },
        {
          "Name": "-f",
          "Description": "Use a specific output format",
          "Aliases": [
            "--format"
          ],
          "Arguments": [
            {
              "Arguments": [
                {
                  "Name": "format",
                  "Description": "format",
                  "Type": "String"
                },
                {
                  "Name": "default",
                  "Description": "format"
                },
                {
                  "Name": "json",
                  "Description": "format"
                },
                {
                  "Name": "unix",
                  "Description": "format"
                },
                {
                  "Name": "checkstyle",
                  "Description": "format"
                },
                {
                  "Name": "github",
                  "Description": "GitHub Actions Annotations"
                }
              ]
            }
          ]
        },
        {
          "Name": "--threads",
          "Description": "Number of threads to use. Set to 1 to use only 1 CPU core",
          "Aliases": [],
          "Arguments": [
            {
              "Arguments": [
                {
                  "Name": "int",
                  "Description": "int",
                  "Type": "String"
                }
              ]
            }
          ]
        },
        {
          "Name": "--rules",
          "Description": "List all available rules",
          "Aliases": [],
          "Arguments": []
        },
        {
          "Name": "-h",
          "Description": "Show help",
          "Aliases": [
            "--help"
          ],
          "Arguments": []
        },
        {
          "Name": "-V",
          "Description": "Show version",
          "Aliases": [
            "--version"
          ],
          "Arguments": []
        }
      ],
      "Optional": true
    },
    {
      "Arguments": [
        {
          "Name": "file|dir|glob",
          "Description": "file|dir|glob",
          "Type": "FileSystemEntry"
        }
      ]
    }
  ]
}