{
  "Comment": "This command info is generated from fig",
  "Name": "quasar",
  "Description": "Quasar Framework CLI",
  "Arguments": [
    {
      "Arguments": [
        {
          "Name": "-h",
          "Description": "Output usage information",
          "Aliases": [
            "--help"
          ],
          "Arguments": []
        }
      ],
      "Optional": true
    },
    {
      "Arguments": [
        {
          "Name": "create",
          "Description": "Create a new Quasar project",
          "Aliases": [],
          "Arguments": [
            {
              "Arguments": [
                {
                  "Name": "--kit",
                  "Description": "Use specific starter kit",
                  "Aliases": [
                    "-k"
                  ],
                  "Arguments": [
                    {
                      "Arguments": [
                        {
                          "Name": "kit",
                          "Description": "kit",
                          "Type": "String"
                        }
                      ]
                    }
                  ]
                },
                {
                  "Name": "--branch",
                  "Description": "Use specific branch of the starter kit",
                  "Aliases": [
                    "-b"
                  ],
                  "Arguments": [
                    {
                      "Arguments": [
                        {
                          "Name": "branch",
                          "Description": "branch",
                          "Type": "String"
                        }
                      ]
                    }
                  ]
                },
                {
                  "Name": "--clone",
                  "Description": "Use git clone",
                  "Aliases": [
                    "-c"
                  ],
                  "Arguments": []
                },
                {
                  "Name": "--offline",
                  "Description": "Use a cached starter kit",
                  "Aliases": [
                    "-o"
                  ],
                  "Arguments": []
                },
                {
                  "Name": "-h",
                  "Description": "Output usage information",
                  "Aliases": [
                    "--help"
                  ],
                  "Arguments": []
                }
              ],
              "Optional": true
            },
            {
              "Arguments": [
                {
                  "Name": "project-name",
                  "Description": "project-name",
                  "Type": "String"
                }
              ]
            }
          ]
        },
        {
          "Name": "info",
          "Description": "Gather environment information for issue reporting",
          "Aliases": [],
          "Arguments": [
            {
              "Arguments": [
                {
                  "Name": "-h",
                  "Description": "Output usage information",
                  "Aliases": [
                    "--help"
                  ],
                  "Arguments": []
                }
              ],
              "Optional": true
            }
          ]
        },
        {
          "Name": "upgrade",
          "Description": "Upgrade Quasar Framework packages",
          "Aliases": [],
          "Arguments": [
            {
              "Arguments": [
                {
                  "Name": "--install",
                  "Description": "Also perform package upgrades",
                  "Aliases": [
                    "-i"
                  ],
                  "Arguments": []
                },
                {
                  "Name": "--prerelease",
                  "Description": "Allow pre-release versions (alpha/beta)",
                  "Aliases": [
                    "-p"
                  ],
                  "Arguments": []
                },
                {
                  "Name": "--major",
                  "Description": "Allow newer major versions (breaking changes)",
                  "Aliases": [
                    "-m"
                  ],
                  "Arguments": []
                },
                {
                  "Name": "-h",
                  "Description": "Output usage information",
                  "Aliases": [
                    "--help"
                  ],
                  "Arguments": []
                }
              ],
              "Optional": true
            }
          ]
        },
        {
          "Name": "serve",
          "Description": "Start development server",
          "Aliases": [],
          "Arguments": [
            {
              "Arguments": [
                {
                  "Name": "--port",
                  "Description": "Port to use",
                  "Aliases": [
                    "-p"
                  ],
                  "Arguments": [
                    {
                      "Arguments": [
                        {
                          "Name": "port",
                          "Description": "port",
                          "Type": "String"
                        }
                      ]
                    }
                  ]
                },
                {
                  "Name": "--hostname",
                  "Description": "Address to use",
                  "Aliases": [
                    "-H"
                  ],
                  "Arguments": [
                    {
                      "Arguments": [
                        {
                          "Name": "hostname",
                          "Description": "hostname",
                          "Type": "String"
                        }
                      ]
                    }
                  ]
                },
                {
                  "Name": "--gzip",
                  "Description": "Compress content",
                  "Aliases": [
                    "-g"
                  ],
                  "Arguments": []
                },
                {
                  "Name": "--silent",
                  "Description": "Suppress log message",
                  "Aliases": [
                    "-s"
                  ],
                  "Arguments": []
                },
                {
                  "Name": "--colors",
                  "Description": "Log messages with colors",
                  "Aliases": [],
                  "Arguments": []
                },
                {
                  "Name": "--open",
                  "Description": "Open browser window after starting",
                  "Aliases": [
                    "-o"
                  ],
                  "Arguments": []
                },
                {
                  "Name": "--cache",
                  "Description": "Cache time (max-age) in seconds",
                  "Aliases": [
                    "-c"
                  ],
                  "Arguments": [
                    {
                      "Arguments": [
                        {
                          "Name": "cache",
                          "Description": "cache",
                          "Type": "String"
                        }
                      ]
                    }
                  ]
                },
                {
                  "Name": "--micro",
                  "Description": "Use micro-cache",
                  "Aliases": [
                    "-m"
                  ],
                  "Arguments": [
                    {
                      "Arguments": [
                        {
                          "Name": "micro",
                          "Description": "micro",
                          "Type": "String"
                        }
                      ]
                    }
                  ]
                },
                {
                  "Name": "--history",
                  "Description": "Use history api fallback",
                  "Aliases": [],
                  "Arguments": []
                },
                {
                  "Name": "--index",
                  "Description": "History mode (only!) index url path",
                  "Aliases": [
                    "-i"
                  ],
                  "Arguments": [
                    {
                      "Arguments": [
                        {
                          "Name": "index",
                          "Description": "index",
                          "Type": "String"
                        }
                      ]
                    }
                  ]
                },
                {
                  "Name": "--https",
                  "Description": "Enable HTTPS",
                  "Aliases": [],
                  "Arguments": []
                },
                {
                  "Name": "--cert",
                  "Description": "Path to SSL cert file (Optional)",
                  "Aliases": [
                    "-C"
                  ],
                  "Arguments": [
                    {
                      "Arguments": [
                        {
                          "Name": "cert",
                          "Description": "cert",
                          "Type": "String"
                        }
                      ]
                    }
                  ]
                },
                {
                  "Name": "--key",
                  "Description": "Path to SSL key file (Optional)",
                  "Aliases": [
                    "-K"
                  ],
                  "Arguments": [
                    {
                      "Arguments": [
                        {
                          "Name": "key",
                          "Description": "key",
                          "Type": "String"
                        }
                      ]
                    }
                  ]
                },
                {
                  "Name": "--proxy",
                  "Description": "Proxy specific requests defined in file",
                  "Aliases": [],
                  "Arguments": [
                    {
                      "Arguments": [
                        {
                          "Name": "proxy",
                          "Description": "proxy",
                          "Type": "String"
                        }
                      ]
                    }
                  ]
                },
                {
                  "Name": "--cors",
                  "Description": "Enable CORS for all requests",
                  "Aliases": [],
                  "Arguments": []
                },
                {
                  "Name": "-h",
                  "Description": "Output usage information",
                  "Aliases": [
                    "--help"
                  ],
                  "Arguments": []
                }
              ],
              "Optional": true
            },
            {
              "Arguments": [
                {
                  "Name": "path",
                  "Description": "path",
                  "Type": "Directory"
                }
              ]
            }
          ]
        }
      ],
      "DontAllowMultiple": true
    }
  ]
}